
[
  { "id": 1, "name": "React", "category": "tech" },
  { "id": 2, "name": "Figma", "category": "design" },
  { "id": 3, "name": "Docker", "category": "tech" },
  { "id": 5, "name": "Node.js", "category": "tech" },
  { "id": 7, "name": "Tailwind CSS", "category": "tech" },
  { "id": 8, "name": "SQL", "category": "data" },
  { "id": 10, "name": "Python", "category": "data" },
  { "id": 11, "name": "Data Analysis", "category": "data" },
  { "id": 12, "name": "Git & GitHub", "category": "tech" },
  { "id": 14, "name": "UX/UI Design", "category": "design" },
  { "id": 16, "name": "JavaScript", "category": "tech" },
  { "id": 17, "name": "TypeScript", "category": "tech" },
  { "id": 18, "name": "Vue.js", "category": "tech" },
  { "id": 19, "name": "Angular", "category": "tech" },
  { "id": 20, "name": "MongoDB", "category": "data" },
  { "id": 21, "name": "PostgreSQL", "category": "data" },
  { "id": 22, "name": "Redis", "category": "data" },
  { "id": 23, "name": "GraphQL", "category": "tech" },
  { "id": 24, "name": "REST APIs", "category": "tech" },
  { "id": 25, "name": "AWS", "category": "tech" },
  { "id": 26, "name": "Azure", "category": "tech" },
  { "id": 27, "name": "Google Cloud", "category": "tech" },
  { "id": 28, "name": "Kubernetes", "category": "tech" },
  { "id": 29, "name": "CI/CD", "category": "tech" },
  { "id": 30, "name": "Jenkins", "category": "tech" },
  { "id": 31, "name": "Adobe Photoshop", "category": "design" },
  { "id": 32, "name": "Adobe Illustrator", "category": "design" },
  { "id": 33, "name": "Sketch", "category": "design" },
  { "id": 34, "name": "Framer", "category": "design" },
  { "id": 35, "name": "Webflow", "category": "design" },
  { "id": 46, "name": "R", "category": "data" },
  { "id": 47, "name": "Machine Learning", "category": "data" },
  { "id": 48, "name": "TensorFlow", "category": "data" },
  { "id": 49, "name": "PyTorch", "category": "data" },
  { "id": 50, "name": "Tableau", "category": "data" },
  { "id": 51, "name": "Power BI", "category": "data" },
  { "id": 52, "name": "Excel", "category": "data" },
  { "id": 53, "name": "Java", "category": "tech" },
  { "id": 54, "name": "C#", "category": "tech" },
  { "id": 55, "name": "C++", "category": "tech" },
  { "id": 56, "name": "PHP", "category": "tech" },
  { "id": 57, "name": "Ruby", "category": "tech" },
  { "id": 58, "name": "Go", "category": "tech" },
  { "id": 59, "name": "Rust", "category": "tech" },
  { "id": 60, "name": "Swift", "category": "tech" },
  { "id": 61, "name": "Kotlin", "category": "tech" },
  { "id": 62, "name": "Flutter", "category": "tech" },
  { "id": 63, "name": "React Native", "category": "tech" },
  { "id": 64, "name": "Ionic", "category": "tech" },
  { "id": 65, "name": "Xamarin", "category": "tech" },
  { "id": 66, "name": "Unity", "category": "tech" },
  { "id": 67, "name": "Unreal Engine", "category": "tech" },
  { "id": 68, "name": "Blender", "category": "design" },
  { "id": 69, "name": "Cinema 4D", "category": "design" },
  { "id": 70, "name": "After Effects", "category": "design" },
  { "id": 71, "name": "Premiere Pro", "category": "design" },
  { "id": 72, "name": "Final Cut Pro", "category": "design" },
  { "id": 80, "name": "WordPress", "category": "tech" },
  { "id": 81, "name": "Shopify", "category": "tech" },
  { "id": 82, "name": "Salesforce", "category": "tech" },
  { "id": 83, "name": "HubSpot", "category": "tech" },
  { "id": 96, "name": "Blockchain", "category": "tech" },
  { "id": 97, "name": "Cryptocurrency", "category": "tech" },
  { "id": 98, "name": "Cybersecurity", "category": "tech" },
  { "id": 99, "name": "Penetration Testing", "category": "tech" },
  { "id": 100, "name": "Network Security", "category": "tech" },
  { "id": 101, "name": "DevOps", "category": "tech" },
  { "id": 102, "name": "Terraform", "category": "tech" },
  { "id": 103, "name": "Ansible", "category": "tech" },
  { "id": 104, "name": "Linux", "category": "tech" },
  { "id": 105, "name": "Windows Server", "category": "tech" },
  { "id": 106, "name": "macOS", "category": "tech" },
  { "id": 107, "name": "Microservices", "category": "tech" },
  { "id": 108, "name": "Serverless", "category": "tech" },
  { "id": 109, "name": "API Design", "category": "tech" },
  { "id": 110, "name": "Database Design", "category": "data" }
]
